odoo/addons/hr_attendance_reason/README.rst
odoo/addons/hr_attendance_reason/__init__.py
odoo/addons/hr_attendance_reason/__manifest__.py
odoo/addons/hr_attendance_reason/data/hr_attendance_reason_data.xml
odoo/addons/hr_attendance_reason/i18n/es.po
odoo/addons/hr_attendance_reason/i18n/hr_attendance_reason.pot
odoo/addons/hr_attendance_reason/i18n/it.po
odoo/addons/hr_attendance_reason/models/__init__.py
odoo/addons/hr_attendance_reason/models/hr_attendance.py
odoo/addons/hr_attendance_reason/models/hr_attendance_reason.py
odoo/addons/hr_attendance_reason/readme/CONTRIBUTORS.rst
odoo/addons/hr_attendance_reason/readme/DESCRIPTION.rst
odoo/addons/hr_attendance_reason/readme/USAGE.rst
odoo/addons/hr_attendance_reason/security/ir.model.access.csv
odoo/addons/hr_attendance_reason/static/description/icon.png
odoo/addons/hr_attendance_reason/static/description/index.html
odoo/addons/hr_attendance_reason/tests/__init__.py
odoo/addons/hr_attendance_reason/tests/test_hr_attendance_reason.py
odoo/addons/hr_attendance_reason/views/hr_attendance_reason_view.xml
odoo/addons/hr_attendance_reason/views/hr_attendance_view.xml
odoo11_addon_hr_attendance_reason-11.0.1.0.0.99.dev13.dist-info/METADATA
odoo11_addon_hr_attendance_reason-11.0.1.0.0.99.dev13.dist-info/WHEEL
odoo11_addon_hr_attendance_reason-11.0.1.0.0.99.dev13.dist-info/top_level.txt
odoo11_addon_hr_attendance_reason-11.0.1.0.0.99.dev13.dist-info/RECORD
